rasahub/__init__.py
rasahub/__main__.py
rasahub/config.py
rasahub/message.py
rasahub/messagehandler.py
rasahub/plugin.py
rasahub/rasahubchannel.py
rasahub/version.py
rasahub-0.3.2.dist-info/LICENSE.txt
rasahub-0.3.2.dist-info/METADATA
rasahub-0.3.2.dist-info/WHEEL
rasahub-0.3.2.dist-info/entry_points.txt
rasahub-0.3.2.dist-info/top_level.txt
rasahub-0.3.2.dist-info/RECORD
