Metadata-Version: 2.1
Name: rasahub
Version: 0.3.2
Summary: Rasahub connects Rasa_core to Humhub Mail
Home-page: UNKNOWN
Author: Christian Frommert
Author-email: christian.frommert@gmail.com
License: MIT
Keywords: humhub rasa rasa_core
Platform: UNKNOWN
Classifier: Development Status :: 3 - Alpha
Classifier: Intended Audience :: Developers
Classifier: License :: OSI Approved :: MIT License
Classifier: Programming Language :: Python :: 2.7
Classifier: Topic :: Software Development
Requires-Dist: PyYaml
Provides-Extra: test
